Metadata-Version: 1.0
Name: binomial-and-gaussian-ditribution
Version: 0.1
Summary: Binomial and Gaussian distributions
Home-page: UNKNOWN
Author: Michael Wambua
Author-email: wambua.m@outlook.com
License: UNKNOWN
Platform: UNKNOWN
